{
    "event": "Miami Grand Prix",
    "date": "April 18, 2026",
    "top_10": [
        {
            "name": "F COLAPINTO",
            "prediction": -7.006725311279297,
            "number": "43",
            "nationality": "ARG",
            "team": "Alpine"
        },
        {
            "name": "A ALBON",
            "prediction": -6.986183166503906,
            "number": "23",
            "nationality": "THA",
            "team": "Williams"
        },
        {
            "name": "V BOTTAS",
            "prediction": -6.976571083068848,
            "number": "77",
            "nationality": "FIN",
            "team": "Cadillac"
        },
        {
            "name": "G BORTOLETO",
            "prediction": -6.832479000091553,
            "number": "5",
            "nationality": "BRA",
            "team": "Audi"
        },
        {
            "name": "F ALONSO",
            "prediction": -6.816959381103516,
            "number": "14",
            "nationality": "ESP",
            "team": "Aston Martin"
        },
        {
            "name": "L STROLL",
            "prediction": -6.737504482269287,
            "number": "18",
            "nationality": "CAN",
            "team": "Aston Martin"
        },
        {
            "name": "N HULKENBERG",
            "prediction": -6.640287399291992,
            "number": "27",
            "nationality": "GER",
            "team": "Audi"
        },
        {
            "name": "P GASLY",
            "prediction": -6.4904327392578125,
            "number": "10",
            "nationality": "FRA",
            "team": "Alpine"
        },
        {
            "name": "S PEREZ",
            "prediction": -6.402397155761719,
            "number": "11",
            "nationality": "MEX",
            "team": "Cadillac"
        },
        {
            "name": "E OCON",
            "prediction": -5.740511894226074,
            "number": "31",
            "nationality": "FRA",
            "team": "Haas F1 Team"
        }
    ]
}