{
    "event": "Miami Grand Prix",
    "date": "April 19, 2026",
    "top_10": [
        {
            "name": "A ALBON",
            "prediction": -8.705596923828125,
            "number": "23",
            "nationality": "THA",
            "team": "Williams"
        },
        {
            "name": "F ALONSO",
            "prediction": -8.206613540649414,
            "number": "14",
            "nationality": "ESP",
            "team": "Aston Martin"
        },
        {
            "name": "V BOTTAS",
            "prediction": -7.956664562225342,
            "number": "77",
            "nationality": "FIN",
            "team": "Cadillac"
        },
        {
            "name": "G BORTOLETO",
            "prediction": -7.076923370361328,
            "number": "5",
            "nationality": "BRA",
            "team": "Audi"
        },
        {
            "name": "N HULKENBERG",
            "prediction": -6.797118663787842,
            "number": "27",
            "nationality": "GER",
            "team": "Audi"
        },
        {
            "name": "O BEARMAN",
            "prediction": -6.429086208343506,
            "number": "87",
            "nationality": "GBR",
            "team": "Haas F1 Team"
        },
        {
            "name": "F COLAPINTO",
            "prediction": -6.373539924621582,
            "number": "43",
            "nationality": "ARG",
            "team": "Alpine"
        },
        {
            "name": "P GASLY",
            "prediction": -5.96519136428833,
            "number": "10",
            "nationality": "FRA",
            "team": "Alpine"
        },
        {
            "name": "L STROLL",
            "prediction": -5.829407691955566,
            "number": "18",
            "nationality": "CAN",
            "team": "Aston Martin"
        },
        {
            "name": "S PEREZ",
            "prediction": -5.519848823547363,
            "number": "11",
            "nationality": "MEX",
            "team": "Cadillac"
        }
    ]
}