{
    "event": "Miami Grand Prix",
    "date": "April 25, 2026",
    "top_10": [
        {
            "name": "L STROLL",
            "prediction": -7.27593469619751,
            "number": "18",
            "nationality": "CAN",
            "team": "Aston Martin"
        },
        {
            "name": "V BOTTAS",
            "prediction": -7.124349594116211,
            "number": "77",
            "nationality": "FIN",
            "team": "Cadillac"
        },
        {
            "name": "F ALONSO",
            "prediction": -7.0788373947143555,
            "number": "14",
            "nationality": "ESP",
            "team": "Aston Martin"
        },
        {
            "name": "F COLAPINTO",
            "prediction": -6.98634147644043,
            "number": "43",
            "nationality": "ARG",
            "team": "Alpine"
        },
        {
            "name": "A ALBON",
            "prediction": -6.95716667175293,
            "number": "23",
            "nationality": "THA",
            "team": "Williams"
        },
        {
            "name": "G BORTOLETO",
            "prediction": -6.630914688110352,
            "number": "5",
            "nationality": "BRA",
            "team": "Audi"
        },
        {
            "name": "S PEREZ",
            "prediction": -6.554506301879883,
            "number": "11",
            "nationality": "MEX",
            "team": "Cadillac"
        },
        {
            "name": "N HULKENBERG",
            "prediction": -6.417835712432861,
            "number": "27",
            "nationality": "GER",
            "team": "Audi"
        },
        {
            "name": "P GASLY",
            "prediction": -6.169484615325928,
            "number": "10",
            "nationality": "FRA",
            "team": "Alpine"
        },
        {
            "name": "E OCON",
            "prediction": -5.384578704833984,
            "number": "31",
            "nationality": "FRA",
            "team": "Haas F1 Team"
        }
    ]
}