{
    "event": "Miami Grand Prix",
    "date": "April 11, 2026",
    "top_10": [
        {
            "name": "F COLAPINTO",
            "prediction": -7.667270183563232,
            "number": "43",
            "nationality": "ARG",
            "team": "Alpine"
        },
        {
            "name": "V BOTTAS",
            "prediction": -7.573357105255127,
            "number": "77",
            "nationality": "FIN",
            "team": "Cadillac"
        },
        {
            "name": "L STROLL",
            "prediction": -7.535802364349365,
            "number": "18",
            "nationality": "CAN",
            "team": "Aston Martin"
        },
        {
            "name": "A ALBON",
            "prediction": -7.3978190422058105,
            "number": "23",
            "nationality": "THA",
            "team": "Williams"
        },
        {
            "name": "S PEREZ",
            "prediction": -7.346325874328613,
            "number": "11",
            "nationality": "MEX",
            "team": "Cadillac"
        },
        {
            "name": "G BORTOLETO",
            "prediction": -7.170650005340576,
            "number": "5",
            "nationality": "BRA",
            "team": "Audi"
        },
        {
            "name": "P GASLY",
            "prediction": -7.127638816833496,
            "number": "10",
            "nationality": "FRA",
            "team": "Alpine"
        },
        {
            "name": "F ALONSO",
            "prediction": -7.112642765045166,
            "number": "14",
            "nationality": "ESP",
            "team": "Aston Martin"
        },
        {
            "name": "N HULKENBERG",
            "prediction": -7.082622051239014,
            "number": "27",
            "nationality": "GER",
            "team": "Audi"
        },
        {
            "name": "E OCON",
            "prediction": -6.370819568634033,
            "number": "31",
            "nationality": "FRA",
            "team": "Haas F1 Team"
        }
    ]
}